README.rst
setup.py
django_x_file_accel_redirects.egg-info/PKG-INFO
django_x_file_accel_redirects.egg-info/SOURCES.txt
django_x_file_accel_redirects.egg-info/dependency_links.txt
django_x_file_accel_redirects.egg-info/requires.txt
django_x_file_accel_redirects.egg-info/top_level.txt
x_file_accel_redirects/__init__.py
x_file_accel_redirects/admin.py
x_file_accel_redirects/conf.py
x_file_accel_redirects/models.py
x_file_accel_redirects/urls.py
x_file_accel_redirects/views.py
x_file_accel_redirects/migrations/0001_initial.py
x_file_accel_redirects/migrations/__init__.py
x_file_accel_redirects/tests/__init__.py
x_file_accel_redirects/tests/test_models.py
x_file_accel_redirects/tests/test_views.py