Metadata-Version: 1.1
Name: django-x_file_accel_redirects
Version: 0.0.1
Summary: Django app to easy configuration of multiple X-File-Accel locations
Home-page: https://github.com/42cc/django-x-file-accel
Author: 42 Coffee Cups
Author-email: contact@42cc.co
License: BSD License
Download-URL: https://github.com/42cc/django-x-file-accel/archive/master.zip
Keywords: ripple,api
Platform: UNKNOWN
Classifier: Environment :: Web Environment
Classifier: Intended Audience :: Developers
Classifier: License :: OSI Approved :: BSD License
Classifier: Programming Language :: Python
Requires: python (>= 2.7)
Requires: django_model_utils
